{
  "fx": {
    "eurusd": 1.1769,
    "gbpusd": 1.3515,
    "usdjpy": 158.92,
    "audusd": 0.716,
    "usdchf": 0.7813,
    "usdcad": 1.369,
    "nzdusd": 0.5884
  },
  "cross": {
    "vix": 19.52,
    "spx": 7126.06,
    "gold": 4811.6,
    "wti": 87.28,
    "dxy": 98.234,
    "move": 65.6953,
    "us2y": 3.78,
    "us10y": 4.246
  },
  "cot": {
    "USD": {
      "net": -3130,
      "we": "2026-04-14"
    },
    "EUR": {
      "net": -72,
      "we": "2026-04-14"
    },
    "GBP": {
      "net": 28426,
      "we": "2026-04-14"
    },
    "JPY": {
      "net": -65309,
      "we": "2026-04-14"
    },
    "AUD": {
      "net": 41675,
      "we": "2026-04-14"
    },
    "CAD": {
      "net": -63570,
      "we": "2026-04-14"
    },
    "CHF": {
      "net": -3693,
      "we": "2026-04-14"
    },
    "NZD": {
      "net": -17090,
      "we": "2026-04-14"
    }
  },
  "headlines": [
    {
      "t": "Are markets waiting for Trump to come to the rescue once again?",
      "time": "09:49"
    },
    {
      "t": "GBP/USD: Political noise and softer BoE pricing \u2013 ING",
      "time": "09:31"
    },
    {
      "t": "BOJ likely to keep monetary policy unchanged in April - report",
      "time": "09:23"
    },
    {
      "t": "Aussie Extends Rally as Risk Appetite Lifts Commodity Currencies",
      "time": "09:03"
    },
    {
      "t": "Canada CPI set to accelerate in March on rising energy costs amid US-Iran war",
      "time": "09:00"
    },
    {
      "t": "AUD/USD picks up to 0.7150 despite rising tesions in the Middle East",
      "time": "08:14"
    },
    {
      "t": "Iran continues to reaffirm that US demands have been \"unserious\" and \"unrealistic\"",
      "time": "08:02"
    },
    {
      "t": "Differences over nuclear programme remains unresolved, says senior Iranian official",
      "time": "07:43"
    }
  ],
  "market_closed": false,
  "saved_at": "2026-04-20T10:16:49Z"
}