{
  "currency": "NZD",
  "country": "Nueva Zelanda",
  "bank": "Banco de la Reserva de Nueva Zelanda (RBNZ)",
  "analysis": "El Banco de la Reserva de Nueva Zelanda (RBNZ) mantiene una tasa de interés del 2.25%, con una postura neutral en cuanto a la política monetaria, considerando una inflación del 3.1% anual, ligeramente por encima del objetivo del banco central. La actividad económica en Nueva Zelanda muestra un crecimiento del PIB del 1.1% anual, con un desempleo del 5.4% y un crecimiento salarial del 2.0% anual, lo que sugiere una economía en expansión moderada.\n\nLa balanza comercial del país se encuentra en equilibrio, con un déficit en la cuenta corriente del 5.7% del PIB, lo que podría generar presión sobre la divisa en el mediano plazo. El sector manufacturero muestra una expansión, con un PMI de 55.2, y las ventas minoristas aumentan un 1.9% mensual, lo que indica una demanda interna sólida. La producción industrial, sin embargo, disminuye un 0.7% mensual, lo que podría ser un indicador de debilidad en el sector.\n\nEl sentimiento de mercado hacia el NZD se ve influenciado por la posición neta de -34.9K contratos en el COT, lo que sugiere una postura bajista por parte de los inversores. El rendimiento del bono a 10 años es del 4.40%, y el rendimiento FX del NZD vs el USD en el último mes es del 3.74%, lo que indica una apreciación reciente de la divisa. El momentum de tasas es negativo, con un cambio del -1.50% en los últimos 12 meses, lo que podría sugerir una tendencia a la baja en las tasas de interés y, por ende, en la divisa.",
  "model": "llama-3.3-70b-versatile",
  "generatedAt": "2026-02-19T15:51:09.188073+00:00",
  "dataSnapshot": {
    "interestRate": 2.25,
    "gdpGrowth": 1.1,
    "inflation": 3.1,
    "unemployment": 5.4,
    "currentAccount": -5.7,
    "cotPositioning": -34900,
    "fxPerformance1M": 3.7402,
    "lastUpdate": "2026-02-19"
  }
}