{
  "generated_at": "2026-07-23T09:05:15Z",
  "sessions": {
    "EUR": {
      "Sydney": "Thin range. EUR/USD 1.1413 anchored by 135bp Fed-ECB carry advantage for USD",
      "Tokyo": "Range-bound. EUR/JPY +0.21% on JPY energy shock despite EU New Car Registrations beat",
      "London": "Hawkish ECB sentiment supports EUR/USD at 1.1413 despite persistent data misses",
      "New York": "Watch for EUR on ECB Interest Rate Decision 12:15 UTC and Press Conference 12:45 UTC"
    },
    "GBP": {
      "Sydney": "Laggard status. GBP/USD 1.3368 under pressure from -12bp SONIA-SOFR carry gap",
      "Tokyo": "GBP/JPY +0.14% in session recap. Broad JPY weakness offsetting negative CESI bias",
      "London": "GBP/USD soft at 1.3368. SONIA 3.73% hold keeps pair sensitive to US inflation headlines",
      "New York": "Watch for GBP on UK Gfk Consumer Confidence 23:01 UTC. Industrial Trends Orders eyed"
    },
    "JPY": {
      "Sydney": "JPY weakness. USD/JPY +0.16% as energy shock headlines drive weaker currency sentiment",
      "Tokyo": "USD/JPY held 163.35. JGB volatility and fiscal concerns outweigh positive CESI data",
      "London": "JPY energy shock persists. USD/JPY bid on 275bp carry as Fed-BoJ divergence dominates",
      "New York": "Watch for JPY on Japan Inflation Rate YoY 23:30 UTC. Forecast 1.7% in focus"
    },
    "AUD": {
      "Sydney": "Bumper employment report drives bid. AUD/USD +0.15% in low liquidity session",
      "Tokyo": "AUD/USD firmed on Employment Change beat of 76.3K vs 15.0K forecast. RBA hike priced",
      "London": "AUD strength leads G10. AUD/JPY +0.37% on 335bp carry and exceptional jobs data",
      "New York": "Carry differential holds. AUD/USD strength persists; no high-impact data scheduled"
    },
    "CAD": {
      "Sydney": "Range-bound. USD/CAD 1.4076. Commodities optimism provides floor despite Fed-BoC gap",
      "Tokyo": "USD/CAD flat at 1.4076. 132bp CORRA-SOFR carry favors USD in quiet regional trade",
      "London": "CAD steady. Crude oil rally to $89.3 supports CAD leg despite BoC on hold at 2.25%",
      "New York": "Watch for CAD on Retail Sales MoM 12:30 UTC. Forecast 1.0% vs previous"
    },
    "CHF": {
      "Sydney": "Thin range. USD/CHF 0.8147. Carry disadvantage persists with SNB at 0.00%",
      "Tokyo": "USD/CHF flat. 375bp Fed-SNB carry spread keeps CHF as a primary funding leg",
      "London": "USD/CHF +0.07% session. Mildly accommodative -0.62% real rate caps CHF upside",
      "New York": "Carry differential holds. USD/CHF bid on rate spread — no scheduled data releases"
    },
    "NZD": {
      "Sydney": "NZD/USD -0.37% during session. Dollar debasement trades offset by 125bp carry gap",
      "Tokyo": "Range-bound. NZD/USD 0.5798. RBNZ hike priced with 94% probability for September",
      "London": "NZD soft. Negative real rate of -1.56% weighs on kiwi vs restrictive G10 peers",
      "New York": "NZD/USD carry intact. No high-impact events scheduled in session window"
    },
    "USD": {
      "Sydney": "USD/JPY +0.16% on crude surge. Dollar debasement theme offset by geopolitical bids",
      "Tokyo": "USD/JPY held 163.35. Bear steepener regime supports USD on Fed inflation rhetoric",
      "London": "USD firms as Fed's Warsh cools inflation expectations. RUBIO Iran comments eyed",
      "New York": "Watch for USD on Chicago Fed National Activity Index 12:30 UTC. 3.75% hold key"
    }
  },
  "session_bucket": "london",
  "news_hash": "['Analysts agree: Hawkish ECB expectations are likely to keep Euro supported', 'Japanese Yen: Energy shock drives weaker currency – MUFG', 'Fed Chair Kevin Warsh Just Threw Cold Water on Investors Who Thought the Worst of Inflation Was Over', 'US Secretary Rubio says price on Iran will get higher every night until they come to their senses', 'Australian Dollar: RBA tone may turn hawkish – Commerzbank', 'BOE rate hike bets ramp up as gilt yields surge higher', 'European Central Bank set to hold interest rates amid cooling inflation and weaker growth', 'Tech capex shock, Yen nursing losses, Aussie jobs beat and ECB decision eyed']"
}