{
  "updated": "2026-04-23T01:30:24Z",
  "source": "mixed",
  "quotes": {
    "vix": {
      "close": 18.92,
      "prev_close": 18.87,
      "chg": -0.58,
      "pct": -2.9744,
      "high": 19.54,
      "low": 18.68,
      "source": "yfinance",
      "pct1w": 8.238,
      "pct1w_date": "2026-04-17"
    },
    "spx": {
      "close": 7137.9,
      "prev_close": 7064.01,
      "chg": 73.8901,
      "pct": 1.046,
      "high": 7138.64,
      "low": 7102.91,
      "source": "yfinance",
      "pct1w": 0.1661,
      "pct1w_date": "2026-04-17"
    },
    "gold": {
      "close": 4752.1,
      "prev_close": 4753.0,
      "chg": -0.8999,
      "pct": -0.0189,
      "high": 4771.3,
      "low": 4710.4,
      "source": "yfinance",
      "pct1w": -2.1719,
      "pct1w_date": "2026-04-17"
    },
    "wti": {
      "close": 93.41,
      "prev_close": 92.96,
      "chg": 0.45,
      "pct": 0.4841,
      "high": 97.22,
      "low": 92.33,
      "source": "yfinance",
      "pct1w": 11.4013,
      "pct1w_date": "2026-04-17"
    },
    "us10y": {
      "close": 4.294,
      "prev_close": 4.292,
      "chg": 0.002,
      "pct": 0.0466,
      "high": 4.304,
      "low": 4.264,
      "source": "yfinance",
      "pct1w": 1.1305,
      "pct1w_date": "2026-04-17"
    },
    "nikkei": {
      "close": 59699.8,
      "prev_close": 59585.86,
      "chg": 113.9414,
      "pct": 0.1912,
      "high": 60013.98,
      "low": 59169.9,
      "source": "yfinance",
      "pct1w": 2.093,
      "pct1w_date": "2026-04-17"
    },
    "stoxx": {
      "close": 5906.22,
      "prev_close": 5930.25,
      "chg": -24.0298,
      "pct": -0.4052,
      "high": null,
      "low": null,
      "source": "yfinance",
      "pct1w": -2.5008,
      "pct1w_date": "2026-04-17"
    },
    "dxy": {
      "close": 98.592,
      "prev_close": 98.59,
      "chg": 0.002,
      "pct": 0.002,
      "high": 98.737,
      "low": 98.552,
      "source": "yfinance",
      "pct1w": 0.5015,
      "pct1w_date": "2026-04-17"
    },
    "us3m": {
      "close": 3.595,
      "prev_close": 3.598,
      "chg": -0.003,
      "pct": -0.0834,
      "high": 3.598,
      "low": 3.595,
      "source": "yfinance",
      "pct1w": -0.1389,
      "pct1w_date": "2026-04-17"
    },
    "us2y": {
      "close": 3.72,
      "prev_close": 3.598,
      "chg": -0.003,
      "pct": -0.0834,
      "source": "fred_dgs2",
      "sourceDate": "2026-04-20"
    },
    "us5y": {
      "close": 3.915,
      "prev_close": 3.908,
      "chg": 0.007,
      "pct": 0.1791,
      "high": 3.925,
      "low": 3.876,
      "source": "yfinance",
      "pct1w": 2.0063,
      "pct1w_date": "2026-04-17"
    },
    "us30y": {
      "close": 4.902,
      "prev_close": 4.898,
      "chg": 0.004,
      "pct": 0.0817,
      "high": 4.909,
      "low": 4.877,
      "source": "yfinance",
      "pct1w": 0.348,
      "pct1w_date": "2026-04-17"
    },
    "move": {
      "close": 69.8789,
      "prev_close": 70.7772,
      "chg": -0.8983,
      "pct": -1.2692,
      "high": null,
      "low": null,
      "source": "yfinance",
      "pct1w": 6.3606,
      "pct1w_date": "2026-04-17"
    },
    "btc": {
      "close": 78102.69,
      "prev_close": 78192.984,
      "chg": 1785.5781,
      "pct": 2.3397,
      "high": 78502.91,
      "low": 77940.78,
      "source": "yfinance",
      "pct1w": 1.2652,
      "pct1w_date": "2026-04-17"
    },
    "ftse": {
      "close": 10476.46,
      "prev_close": 10498.09,
      "chg": -21.6299,
      "pct": -0.206,
      "high": 10523.17,
      "low": 10468.03,
      "source": "yfinance",
      "pct1w": -1.7918,
      "pct1w_date": "2026-04-17"
    },
    "asx": {
      "close": 8807.8,
      "prev_close": 8843.6,
      "chg": -35.7998,
      "pct": -0.4048,
      "high": 8843.6,
      "low": 8747.8,
      "source": "yfinance",
      "pct1w": -1.5547,
      "pct1w_date": "2026-04-17"
    },
    "nzx": {
      "close": 12890.26,
      "prev_close": 12945.6,
      "chg": -55.3398,
      "pct": -0.4275,
      "high": 13013.1,
      "low": 12868.0,
      "source": "yfinance",
      "pct1w": -0.1194,
      "pct1w_date": "2026-04-17"
    },
    "eurusd": {
      "close": 1.1712,
      "prev_close": 1.1711,
      "chg": 0.0001,
      "pct": 0.0117,
      "high": 1.1716,
      "low": 1.1696,
      "source": "yfinance",
      "pct1w": -0.5973,
      "pct1w_date": "2026-04-17",
      "hv30": 7.96,
      "pct1m": 1.3165,
      "pct1m_date": "2026-03-23"
    },
    "gbpusd": {
      "close": 1.3502,
      "prev_close": 1.3508,
      "chg": -0.0006,
      "pct": -0.0461,
      "high": 1.351,
      "low": 1.348,
      "source": "yfinance",
      "pct1w": -0.1813,
      "pct1w_date": "2026-04-17",
      "hv30": 8.87,
      "pct1m": 1.2755,
      "pct1m_date": "2026-03-23"
    },
    "usdjpy": {
      "close": 159.403,
      "prev_close": 159.36,
      "chg": 0.043,
      "pct": 0.027,
      "high": 159.687,
      "low": 159.272,
      "source": "yfinance",
      "pct1w": 0.1307,
      "pct1w_date": "2026-04-17",
      "hv30": 6.63,
      "pct1m": 0.1049,
      "pct1m_date": "2026-03-23"
    },
    "audusd": {
      "close": 0.7158,
      "prev_close": 0.7161,
      "chg": -0.0003,
      "pct": -0.0401,
      "high": 0.7165,
      "low": 0.7137,
      "source": "yfinance",
      "pct1w": -0.0127,
      "pct1w_date": "2026-04-17",
      "hv30": 12.32,
      "pct1m": 2.1446,
      "pct1m_date": "2026-03-23"
    },
    "usdchf": {
      "close": 0.7845,
      "prev_close": 0.7841,
      "chg": 0.0004,
      "pct": 0.0548,
      "high": 0.7859,
      "low": 0.7836,
      "source": "yfinance",
      "pct1w": 0.1634,
      "pct1w_date": "2026-04-17",
      "hv30": 7.85,
      "pct1m": -0.4252,
      "pct1m_date": "2026-03-23"
    },
    "usdcad": {
      "close": 1.3668,
      "prev_close": 1.3669,
      "chg": -0.0001,
      "pct": -0.008,
      "high": 1.3679,
      "low": 1.366,
      "source": "yfinance",
      "pct1w": -0.238,
      "pct1w_date": "2026-04-17",
      "hv30": 4.61,
      "pct1m": -0.3085,
      "pct1m_date": "2026-03-23"
    },
    "nzdusd": {
      "close": 0.5908,
      "prev_close": 0.5909,
      "chg": -0.0001,
      "pct": -0.0177,
      "high": 0.5911,
      "low": 0.589,
      "source": "yfinance",
      "pct1w": 0.3675,
      "pct1w_date": "2026-04-17",
      "hv30": 11.2,
      "pct1m": 1.3121,
      "pct1m_date": "2026-03-23"
    },
    "eurgbp": {
      "close": 0.8672,
      "prev_close": 0.8666,
      "chg": 0.0006,
      "pct": 0.0727,
      "high": 0.8676,
      "low": 0.8662,
      "source": "yfinance",
      "pct1w": -0.4306,
      "pct1w_date": "2026-04-17",
      "hv30": 3.19,
      "pct1m": 0.0127,
      "pct1m_date": "2026-03-23"
    },
    "eurjpy": {
      "close": 186.629,
      "prev_close": 186.592,
      "chg": 0.037,
      "pct": 0.0198,
      "high": 186.756,
      "low": 186.55,
      "source": "yfinance",
      "pct1w": -0.4953,
      "pct1w_date": "2026-04-17",
      "hv30": 4.85,
      "pct1m": 1.3918,
      "pct1m_date": "2026-03-23"
    },
    "eurchf": {
      "close": 0.9185,
      "prev_close": 0.9181,
      "chg": 0.0004,
      "pct": 0.0403,
      "high": 0.919,
      "low": 0.9178,
      "source": "yfinance",
      "pct1w": -0.4444,
      "pct1w_date": "2026-04-17",
      "hv30": 4.23,
      "pct1m": 0.8499,
      "pct1m_date": "2026-03-23"
    },
    "eurcad": {
      "close": 1.6001,
      "prev_close": 1.5996,
      "chg": 0.0005,
      "pct": 0.0294,
      "high": 1.6005,
      "low": 1.5989,
      "source": "yfinance",
      "pct1w": -0.8428,
      "pct1w_date": "2026-04-17",
      "hv30": 5.68,
      "pct1m": 0.9591,
      "pct1m_date": "2026-03-23"
    },
    "euraud": {
      "close": 1.6368,
      "prev_close": 1.6342,
      "chg": 0.0025,
      "pct": 0.1542,
      "high": 1.6384,
      "low": 1.6338,
      "source": "yfinance",
      "pct1w": -0.5372,
      "pct1w_date": "2026-04-17",
      "hv30": 6.38,
      "pct1m": -0.7736,
      "pct1m_date": "2026-03-23"
    },
    "gbpjpy": {
      "close": 215.202,
      "prev_close": 215.25,
      "chg": -0.048,
      "pct": -0.0223,
      "high": 215.355,
      "low": 215.143,
      "source": "yfinance",
      "pct1w": -0.0543,
      "pct1w_date": "2026-04-17",
      "hv30": 5.1,
      "pct1m": 1.3875,
      "pct1m_date": "2026-03-23"
    },
    "gbpchf": {
      "close": 1.0591,
      "prev_close": 1.059,
      "chg": 0.0,
      "pct": 0.0047,
      "high": 1.0597,
      "low": 1.0584,
      "source": "yfinance",
      "pct1w": -0.0113,
      "pct1w_date": "2026-04-17",
      "hv30": 4.86,
      "pct1m": 0.837,
      "pct1m_date": "2026-03-23"
    },
    "gbpcad": {
      "close": 1.8448,
      "prev_close": 1.8454,
      "chg": -0.0006,
      "pct": -0.0325,
      "high": 1.8467,
      "low": 1.8431,
      "source": "yfinance",
      "pct1w": -0.4259,
      "pct1w_date": "2026-04-17",
      "hv30": 6.72,
      "pct1m": 0.9565,
      "pct1m_date": "2026-03-23"
    },
    "audjpy": {
      "close": 114.019,
      "prev_close": 114.047,
      "chg": -0.028,
      "pct": -0.0246,
      "high": 114.218,
      "low": 113.935,
      "source": "yfinance",
      "pct1w": 0.05,
      "pct1w_date": "2026-04-17",
      "hv30": 8.76,
      "pct1m": 2.1921,
      "pct1m_date": "2026-03-23"
    },
    "audnzd": {
      "close": 1.2118,
      "prev_close": 1.2115,
      "chg": 0.0003,
      "pct": 0.0231,
      "high": 1.2128,
      "low": 1.2096,
      "source": "yfinance",
      "pct1w": -0.37,
      "pct1w_date": "2026-04-17",
      "hv30": 4.92,
      "pct1m": 0.8346,
      "pct1m_date": "2026-03-23"
    },
    "audchf": {
      "close": 0.561,
      "prev_close": 0.5609,
      "chg": 0.0002,
      "pct": 0.0285,
      "high": 0.562,
      "low": 0.5601,
      "source": "yfinance",
      "pct1w": 0.0767,
      "pct1w_date": "2026-04-17",
      "hv30": 7.66,
      "pct1m": 1.6363,
      "pct1m_date": "2026-03-23"
    },
    "cadjpy": {
      "close": 116.632,
      "prev_close": 116.573,
      "chg": 0.059,
      "pct": 0.0506,
      "high": 116.754,
      "low": 116.549,
      "source": "yfinance",
      "pct1w": 0.3804,
      "pct1w_date": "2026-04-17",
      "hv30": 6.42,
      "pct1m": 0.4366,
      "pct1m_date": "2026-03-23"
    },
    "chfjpy": {
      "close": 203.155,
      "prev_close": 203.213,
      "chg": -0.058,
      "pct": -0.0285,
      "high": 203.308,
      "low": 203.052,
      "source": "yfinance",
      "pct1w": -0.0418,
      "pct1w_date": "2026-04-17",
      "hv30": 6.29,
      "pct1m": 0.5428,
      "pct1m_date": "2026-03-23"
    },
    "nzdjpy": {
      "close": 94.067,
      "prev_close": 94.124,
      "chg": -0.057,
      "pct": -0.0606,
      "high": 94.204,
      "low": 93.99,
      "source": "yfinance",
      "pct1w": 0.412,
      "pct1w_date": "2026-04-17",
      "hv30": 7.12,
      "pct1m": 1.3552,
      "pct1m_date": "2026-03-23"
    },
    "eurnzd": {
      "close": 1.9835,
      "prev_close": 1.9815,
      "chg": 0.002,
      "pct": 0.1009,
      "high": 1.9859,
      "low": 1.9804,
      "source": "yfinance",
      "pct1w": -0.8686,
      "pct1w_date": "2026-04-17",
      "hv30": 5.22,
      "pct1m": 0.0509,
      "pct1m_date": "2026-03-23"
    },
    "gbpaud": {
      "close": 1.8872,
      "prev_close": 1.8857,
      "chg": 0.0014,
      "pct": 0.0764,
      "high": 1.8887,
      "low": 1.8839,
      "source": "yfinance",
      "pct1w": -0.1038,
      "pct1w_date": "2026-04-17",
      "hv30": 6.64,
      "pct1m": -0.7902,
      "pct1m_date": "2026-03-23"
    },
    "gbpnzd": {
      "close": 2.2869,
      "prev_close": 2.285,
      "chg": 0.0019,
      "pct": 0.0818,
      "high": 2.2892,
      "low": 2.2831,
      "source": "yfinance",
      "pct1w": -0.4657,
      "pct1w_date": "2026-04-17",
      "hv30": 4.68,
      "pct1m": 0.0267,
      "pct1m_date": "2026-03-23"
    },
    "audcad": {
      "close": 0.9775,
      "prev_close": 0.9782,
      "chg": -0.0008,
      "pct": -0.0787,
      "high": 0.9791,
      "low": 0.9752,
      "source": "yfinance",
      "pct1w": -0.3375,
      "pct1w_date": "2026-04-17",
      "hv30": 9.4,
      "pct1m": 1.7657,
      "pct1m_date": "2026-03-23"
    },
    "cadchf": {
      "close": 0.574,
      "prev_close": 0.5736,
      "chg": 0.0004,
      "pct": 0.0662,
      "high": 0.5746,
      "low": 0.5728,
      "source": "yfinance",
      "pct1w": 0.4181,
      "pct1w_date": "2026-04-17",
      "hv30": 4.85,
      "pct1m": -0.1062,
      "pct1m_date": "2026-03-23"
    },
    "nzdcad": {
      "close": 0.8065,
      "prev_close": 0.8072,
      "chg": -0.0006,
      "pct": -0.0805,
      "high": 0.8075,
      "low": 0.8051,
      "source": "yfinance",
      "pct1w": 0.0372,
      "pct1w_date": "2026-04-17",
      "hv30": 8.21,
      "pct1m": 0.9134,
      "pct1m_date": "2026-03-23"
    },
    "nzdchf": {
      "close": 0.463,
      "prev_close": 0.4631,
      "chg": -0.0001,
      "pct": -0.0238,
      "high": 0.4636,
      "low": 0.4608,
      "source": "yfinance",
      "pct1w": 0.5189,
      "pct1w_date": "2026-04-17",
      "hv30": 6.37,
      "pct1m": 0.81,
      "pct1m_date": "2026-03-23"
    }
  },
  "hv30": {
    "eurusd": 7.96,
    "gbpusd": 8.87,
    "usdjpy": 6.63,
    "audusd": 12.32,
    "usdchf": 7.85,
    "usdcad": 4.61,
    "nzdusd": 11.2,
    "eurgbp": 3.19,
    "eurjpy": 4.85,
    "eurchf": 4.23,
    "eurcad": 5.68,
    "euraud": 6.38,
    "gbpjpy": 5.1,
    "gbpchf": 4.86,
    "gbpcad": 6.72,
    "audjpy": 8.76,
    "audnzd": 4.92,
    "audchf": 7.66,
    "cadjpy": 6.42,
    "chfjpy": 6.29,
    "nzdjpy": 7.12,
    "eurnzd": 5.22,
    "gbpaud": 6.64,
    "gbpnzd": 4.68,
    "audcad": 9.4,
    "cadchf": 4.85,
    "nzdcad": 8.21,
    "nzdchf": 6.37
  },
  "correlations": [
    {
      "a": "EUR/USD",
      "b": "DXY",
      "corr30": -0.861,
      "n30": 30,
      "corr": -0.898,
      "n": 60,
      "corr90": -0.843,
      "n90": 90,
      "norm": -0.451,
      "z_score": -1.21
    },
    {
      "a": "AUD/USD",
      "b": "Gold",
      "corr30": 0.542,
      "n30": 30,
      "corr": 0.403,
      "n": 60,
      "corr90": 0.76,
      "n90": 90,
      "norm": 0.288,
      "z_score": 0.24
    },
    {
      "a": "USD/JPY",
      "b": "US 10Y",
      "corr30": 0.248,
      "n30": 30,
      "corr": 0.591,
      "n": 60,
      "corr90": 0.501,
      "n90": 90,
      "norm": 0.051,
      "z_score": 1.49
    },
    {
      "a": "USD/JPY",
      "b": "VIX",
      "corr30": 0.063,
      "n30": 30,
      "corr": 0.529,
      "n": 60,
      "corr90": 0.459,
      "n90": 90,
      "norm": 0.06,
      "z_score": 1.22
    },
    {
      "a": "USD/CAD",
      "b": "WTI Oil",
      "corr30": 0.616,
      "n30": 30,
      "corr": 0.695,
      "n": 60,
      "corr90": 0.229,
      "n90": 90,
      "norm": -0.022,
      "z_score": 1.64
    },
    {
      "a": "GBP/USD",
      "b": "FTSE 100",
      "corr30": 0.587,
      "n30": 30,
      "corr": 0.164,
      "n": 60,
      "corr90": 0.062,
      "n90": 90,
      "norm": -0.099,
      "z_score": 0.49
    },
    {
      "a": "AUD/USD",
      "b": "ASX 200",
      "corr30": 0.688,
      "n30": 30,
      "corr": 0.503,
      "n": 60,
      "corr90": 0.434,
      "n90": 90,
      "norm": 0.156,
      "z_score": 0.77
    },
    {
      "a": "NZD/USD",
      "b": "NZX 50",
      "corr30": 0.249,
      "n30": 30,
      "corr": 0.648,
      "n": 60,
      "corr90": 0.134,
      "n90": 90,
      "norm": -0.272,
      "z_score": 2.16
    },
    {
      "a": "EUR/USD",
      "b": "EuroStoxx",
      "corr30": 0.669,
      "n30": 30,
      "corr": 0.725,
      "n": 60,
      "corr90": 0.538,
      "n90": 90,
      "norm": -0.145,
      "z_score": 1.75
    },
    {
      "a": "GBP/USD",
      "b": "Gold",
      "corr30": 0.155,
      "n30": 30,
      "corr": 0.302,
      "n": 60,
      "corr90": 0.255,
      "n90": 90,
      "norm": 0.203,
      "z_score": 0.23
    },
    {
      "a": "DXY",
      "b": "SPX",
      "corr30": -0.891,
      "n30": 30,
      "corr": -0.76,
      "n": 60,
      "corr90": -0.673,
      "n90": 90,
      "norm": -0.335,
      "z_score": -1.0
    },
    {
      "a": "Gold",
      "b": "DXY",
      "corr30": -0.139,
      "n30": 30,
      "corr": -0.471,
      "n": 60,
      "corr90": -0.316,
      "n90": 90,
      "norm": -0.304,
      "z_score": -0.37
    }
  ],
  "fx_etf_iv": {
    "eurusd": {
      "iv": 7.1,
      "source": "CBOE ^EUVIX",
      "iv_rank": null,
      "iv_pct_rank": null,
      "iv_hist_n": 1
    },
    "gbpusd": {
      "iv": 11.0,
      "source": "CBOE ^BPVIX",
      "iv_rank": null,
      "iv_pct_rank": null,
      "iv_hist_n": 1
    },
    "usdjpy": {
      "iv": 7.2,
      "source": "CBOE ^JYVIX",
      "iv_rank": null,
      "iv_pct_rank": null,
      "iv_hist_n": 1
    },
    "audusd": {
      "iv": 15.9,
      "expiry": "2026-05-15",
      "atm": 71.0,
      "source": "FXA options",
      "iv_rank": null,
      "iv_pct_rank": null,
      "iv_hist_n": 1
    },
    "usdchf": {
      "iv": 23.8,
      "expiry": "2026-05-15",
      "atm": 112.0,
      "source": "FXF options",
      "iv_rank": null,
      "iv_pct_rank": null,
      "iv_hist_n": 1
    },
    "usdcad": null,
    "nzdusd": {
      "iv": 17.2,
      "source": "est. CBOE ^AUDVIX \u00d7 1.08",
      "iv_rank": null,
      "iv_pct_rank": null,
      "iv_hist_n": 1
    }
  },
  "var_cvar": {
    "eurusd": {
      "var_pct": 0.6842,
      "cvar_pct": 0.8863,
      "var60_pct": 0.7333,
      "n": 252,
      "confidence": 0.95
    },
    "gbpusd": {
      "var_pct": 0.7096,
      "cvar_pct": 0.8592,
      "var60_pct": 0.7883,
      "n": 252,
      "confidence": 0.95
    },
    "usdjpy": {
      "var_pct": 0.7329,
      "cvar_pct": 1.1708,
      "var60_pct": 0.7927,
      "n": 252,
      "confidence": 0.95
    },
    "audusd": {
      "var_pct": 0.8306,
      "cvar_pct": 1.028,
      "var60_pct": 1.1215,
      "n": 252,
      "confidence": 0.95
    },
    "usdchf": {
      "var_pct": 0.9323,
      "cvar_pct": 1.1905,
      "var60_pct": 0.9695,
      "n": 252,
      "confidence": 0.95
    },
    "usdcad": {
      "var_pct": 0.5077,
      "cvar_pct": 0.6545,
      "var60_pct": 0.5016,
      "n": 252,
      "confidence": 0.95
    },
    "nzdusd": {
      "var_pct": 0.9261,
      "cvar_pct": 1.0776,
      "var60_pct": 1.0125,
      "n": 252,
      "confidence": 0.95
    },
    "spx": {
      "var_pct": 1.3701,
      "cvar_pct": 1.7301,
      "var60_pct": 1.5785,
      "n": 252,
      "confidence": 0.95
    },
    "gold": {
      "var_pct": 2.8695,
      "cvar_pct": 4.6568,
      "var60_pct": 3.9062,
      "n": 252,
      "confidence": 0.95
    },
    "wti": {
      "var_pct": 4.2674,
      "cvar_pct": 8.3882,
      "var60_pct": 12.1579,
      "n": 252,
      "confidence": 0.95
    },
    "dxy": {
      "var_pct": 0.691,
      "cvar_pct": 0.8412,
      "var60_pct": 0.8331,
      "n": 252,
      "confidence": 0.95
    },
    "us10y": {
      "var_pct": 1.6298,
      "cvar_pct": 2.0417,
      "var60_pct": 1.5321,
      "n": 252,
      "confidence": 0.95
    },
    "btc": {
      "var_pct": 3.96,
      "cvar_pct": 6.017,
      "var60_pct": 3.6884,
      "n": 252,
      "confidence": 0.95
    },
    "vix": {
      "var_pct": 13.2617,
      "cvar_pct": 16.5962,
      "var60_pct": 15.9895,
      "n": 252,
      "confidence": 0.95
    },
    "move": {
      "var_pct": 7.3233,
      "cvar_pct": 9.2282,
      "var60_pct": 10.3382,
      "n": 252,
      "confidence": 0.95
    }
  }
}