{
  "updated": "2026-04-02T08:25:24Z",
  "source": "mixed",
  "quotes": {
    "vix": {
      "close": 26.42,
      "prev_close": 24.54,
      "chg": 1.88,
      "pct": 7.661,
      "high": 26.79,
      "low": 26.23,
      "source": "yfinance"
    },
    "spx": {
      "close": 6575.3198,
      "prev_close": 6528.52,
      "chg": 46.7998,
      "pct": 0.7169,
      "high": 6609.6699,
      "low": 6554.29,
      "source": "yfinance"
    },
    "gold": {
      "close": 4665.5,
      "prev_close": 4783.2002,
      "chg": -117.7002,
      "pct": -2.4607,
      "high": 4825.8999,
      "low": 4580.3999,
      "source": "yfinance"
    },
    "wti": {
      "close": 106.88,
      "prev_close": 100.12,
      "chg": 6.76,
      "pct": 6.7519,
      "high": 107.05,
      "low": 97.5,
      "source": "yfinance"
    },
    "us10y": {
      "close": 4.319,
      "prev_close": 4.311,
      "chg": 0.008,
      "pct": 0.1856,
      "high": 4.334,
      "low": 4.293,
      "source": "yfinance"
    },
    "nikkei": {
      "close": 52463.2695,
      "prev_close": 53739.6797,
      "chg": -1276.4102,
      "pct": -2.3752,
      "high": 54258.4805,
      "low": 52273.0703,
      "source": "yfinance"
    },
    "stoxx": {
      "close": 5638.0898,
      "prev_close": 5732.71,
      "chg": -94.6201,
      "pct": -1.6505,
      "high": 5672.1299,
      "low": 5624.73,
      "source": "yfinance"
    },
    "dxy": {
      "close": 100.07,
      "prev_close": 99.65,
      "chg": 0.42,
      "pct": 0.4215,
      "high": 100.172,
      "low": 99.447,
      "source": "yfinance"
    },
    "us3m": {
      "close": 3.605,
      "prev_close": 3.6,
      "chg": 0.005,
      "pct": 0.1389,
      "high": 3.605,
      "low": 3.6,
      "source": "yfinance"
    },
    "us2y": {
      "close": 3.79,
      "prev_close": 3.6,
      "chg": 0.005,
      "pct": 0.1389,
      "source": "fred_dgs2",
      "sourceDate": "2026-03-31"
    },
    "us5y": {
      "close": 3.955,
      "prev_close": 3.945,
      "chg": 0.01,
      "pct": 0.2535,
      "high": 3.967,
      "low": 3.917,
      "source": "yfinance"
    },
    "us30y": {
      "close": 4.9,
      "prev_close": 4.891,
      "chg": 0.009,
      "pct": 0.184,
      "high": 4.919,
      "low": 4.884,
      "source": "yfinance"
    },
    "move": {
      "close": 90.19,
      "prev_close": 96.05,
      "chg": -5.86,
      "pct": -6.101,
      "high": 96.05,
      "low": 90.19,
      "source": "yfinance"
    },
    "btc": {
      "close": 66629.2188,
      "prev_close": 68078.5547,
      "chg": -1449.3359,
      "pct": -2.1289,
      "high": 68588.5391,
      "low": 66268.8438,
      "source": "yfinance"
    },
    "eurusd": {
      "close": 1.153,
      "prev_close": 1.1574,
      "chg": -0.0044,
      "pct": -0.3816,
      "high": 1.1606,
      "low": 1.1519,
      "source": "yfinance",
      "hv30": 7.95
    },
    "gbpusd": {
      "close": 1.3205,
      "prev_close": 1.3243,
      "chg": -0.0039,
      "pct": -0.2917,
      "high": 1.3319,
      "low": 1.3202,
      "source": "yfinance",
      "hv30": 8.21
    },
    "usdjpy": {
      "close": 159.623,
      "prev_close": 158.579,
      "chg": 1.044,
      "pct": 0.6584,
      "high": 159.713,
      "low": 158.528,
      "source": "yfinance",
      "hv30": 7.69
    },
    "audusd": {
      "close": 0.6875,
      "prev_close": 0.6921,
      "chg": -0.0045,
      "pct": -0.6545,
      "high": 0.6935,
      "low": 0.6866,
      "source": "yfinance",
      "hv30": 11.91
    },
    "usdchf": {
      "close": 0.7994,
      "prev_close": 0.7976,
      "chg": 0.0018,
      "pct": 0.2219,
      "high": 0.8003,
      "low": 0.7927,
      "source": "yfinance",
      "hv30": 6.91
    },
    "usdcad": {
      "close": 1.3913,
      "prev_close": 1.3903,
      "chg": 0.001,
      "pct": 0.0712,
      "high": 1.3918,
      "low": 1.3864,
      "source": "yfinance",
      "hv30": 3.69
    },
    "nzdusd": {
      "close": 0.5713,
      "prev_close": 0.5756,
      "chg": -0.0043,
      "pct": -0.7546,
      "high": 0.5758,
      "low": 0.5702,
      "source": "yfinance",
      "hv30": 10.89
    },
    "eurgbp": {
      "close": 0.8729,
      "prev_close": 0.8739,
      "chg": -0.001,
      "pct": -0.1099,
      "high": 0.8729,
      "low": 0.8702,
      "source": "yfinance",
      "hv30": 3.93
    },
    "eurjpy": {
      "close": 183.962,
      "prev_close": 183.475,
      "chg": 0.487,
      "pct": 0.2654,
      "high": 184.162,
      "low": 183.485,
      "source": "yfinance",
      "hv30": 4.9
    },
    "eurchf": {
      "close": 0.9214,
      "prev_close": 0.9232,
      "chg": -0.0018,
      "pct": -0.1928,
      "high": 0.9223,
      "low": 0.9191,
      "source": "yfinance",
      "hv30": 5.52
    },
    "eurcad": {
      "close": 1.6035,
      "prev_close": 1.6087,
      "chg": -0.0052,
      "pct": -0.3232,
      "high": 1.6094,
      "low": 1.602,
      "source": "yfinance",
      "hv30": 7.3
    },
    "euraud": {
      "close": 1.6766,
      "prev_close": 1.6724,
      "chg": 0.0042,
      "pct": 0.2535,
      "high": 1.6788,
      "low": 1.671,
      "source": "yfinance",
      "hv30": 7.64
    },
    "gbpjpy": {
      "close": 210.737,
      "prev_close": 209.941,
      "chg": 0.796,
      "pct": 0.3792,
      "high": 211.28,
      "low": 210.334,
      "source": "yfinance",
      "hv30": 5.81
    },
    "gbpchf": {
      "close": 1.0555,
      "prev_close": 1.0563,
      "chg": -0.0007,
      "pct": -0.0701,
      "high": 1.057,
      "low": 1.0547,
      "source": "yfinance",
      "hv30": 6.87
    },
    "gbpcad": {
      "close": 1.8368,
      "prev_close": 1.8406,
      "chg": -0.0038,
      "pct": -0.2064,
      "high": 1.8472,
      "low": 1.8365,
      "source": "yfinance",
      "hv30": 7.58
    },
    "audjpy": {
      "close": 109.712,
      "prev_close": 109.706,
      "chg": 0.006,
      "pct": 0.0055,
      "high": 110.085,
      "low": 109.396,
      "source": "yfinance",
      "hv30": 9.31
    },
    "audnzd": {
      "close": 1.2037,
      "prev_close": 1.2024,
      "chg": 0.0014,
      "pct": 0.1131,
      "high": 1.2054,
      "low": 1.2025,
      "source": "yfinance",
      "hv30": 5.26
    },
    "audchf": {
      "close": 0.5495,
      "prev_close": 0.5519,
      "chg": -0.0025,
      "pct": -0.4457,
      "high": 0.5503,
      "low": 0.5476,
      "source": "yfinance",
      "hv30": 10.27
    },
    "cadjpy": {
      "close": 114.721,
      "prev_close": 114.037,
      "chg": 0.684,
      "pct": 0.5998,
      "high": 114.829,
      "low": 114.249,
      "source": "yfinance",
      "hv30": 7.88
    },
    "chfjpy": {
      "close": 199.617,
      "prev_close": 198.715,
      "chg": 0.902,
      "pct": 0.4539,
      "high": 200.084,
      "low": 199.053,
      "source": "yfinance",
      "hv30": 7.09
    },
    "nzdjpy": {
      "close": 91.122,
      "prev_close": 91.221,
      "chg": -0.099,
      "pct": -0.1085,
      "high": 91.339,
      "low": 90.817,
      "source": "yfinance",
      "hv30": 7.32
    }
  },
  "hv30": {
    "eurusd": 7.95,
    "gbpusd": 8.21,
    "usdjpy": 7.69,
    "audusd": 11.91,
    "usdchf": 6.91,
    "usdcad": 3.69,
    "nzdusd": 10.89,
    "eurgbp": 3.93,
    "eurjpy": 4.9,
    "eurchf": 5.52,
    "eurcad": 7.3,
    "euraud": 7.64,
    "gbpjpy": 5.81,
    "gbpchf": 6.87,
    "gbpcad": 7.58,
    "audjpy": 9.31,
    "audnzd": 5.26,
    "audchf": 10.27,
    "cadjpy": 7.88,
    "chfjpy": 7.09,
    "nzdjpy": 7.32
  },
  "correlations": [
    {
      "a": "EUR/USD",
      "b": "DXY",
      "corr": -0.955,
      "n": 60
    },
    {
      "a": "AUD/USD",
      "b": "Gold",
      "corr": 0.652,
      "n": 60
    },
    {
      "a": "USD/JPY",
      "b": "US 10Y",
      "corr": 0.477,
      "n": 60
    },
    {
      "a": "USD/JPY",
      "b": "VIX",
      "corr": 0.508,
      "n": 60
    },
    {
      "a": "USD/CAD",
      "b": "WTI Oil",
      "corr": 0.11,
      "n": 60
    }
  ]
}