{
  "updated_utc": "2026-07-08T12:41:20.421155+00:00",
  "updated_label": "12:41 UTC",
  "total": 52,
  "total_high": 28,
  "total_med": 7,
  "sources_active": [
    "ActionForex",
    "BabyPips",
    "FXStreet",
    "Finnhub",
    "InvestMacro",
    "Nasdaq FX",
    "RBA",
    "RTT News",
    "Riksbank"
  ],
  "lang_counts": {
    "es": 0,
    "en": 52
  },
  "articles": [
    {
      "id": "1106d82aee86",
      "cur": "USD",
      "impact": "high",
      "title": "Dollar Edges Up on Weak Stocks and Crude Oil Strength",
      "expand": "The dollar index (DXY00 ) rose by +0.24% on Tuesday. The dollar rose on Tuesday amid weakness in stocks, boosting liquidity demand for the currency. Also, higher crude oil prices on Tuesday pushed up inflation expectations and could persuade the Fed to keep monetary policy tight, a supportive factor for...",
      "source": "Nasdaq FX",
      "link": "https://www.nasdaq.com/articles/dollar-edges-weak-stocks-and-crude-oil-strength",
      "time": "12:40",
      "ts": 1783514436000,
      "featured": true,
      "lang": "en",
      "date": "08 Jul",
      "datetime": "2026-07-08T12:40:36+00:00",
      "recent": true
    },
    {
      "id": "bda8d074bbf2",
      "cur": "USD",
      "impact": "high",
      "title": "Crude Oil Prices Sharply Higher on Supply Disruptions",
      "expand": "August WTI crude oil (CLQ26 ) on Tuesday closed up +1.89 (+2.76%), and August RBOB gasoline (RBQ26 ) closed down -0.0494 (-1.64%). Crude oil and gasoline prices settled mixed on Tuesday. Crude oil prices jumped following attacks on shipping in and around the Strait of Hormuz. Gasoline prices retreated on...",
      "source": "Nasdaq FX",
      "link": "https://www.nasdaq.com/articles/crude-oil-prices-sharply-higher-supply-disruptions",
      "time": "12:40",
      "ts": 1783514435000,
      "featured": true,
      "lang": "en",
      "date": "08 Jul",
      "datetime": "2026-07-08T12:40:35+00:00",
      "recent": true
    },
    {
      "id": "4fd7d10e6c4b",
      "cur": "USD",
      "impact": "high",
      "title": "Cotton Extends Rally to Tuesday, Nearing Limit Gains",
      "expand": "Cotton futures closed with contracts 99 to 299 points higher, with some contracts hitting the three cent limit at the high. The outside markets were mixed, as Crude oil was up $3.65 following Iran striking vessels in the Strait of Hormuz overnight. The US responded by revoking waivers authorizing Iran...",
      "source": "Nasdaq FX",
      "link": "https://www.nasdaq.com/articles/cotton-extends-rally-tuesday-nearing-limit-gains",
      "time": "12:31",
      "ts": 1783513880000,
      "featured": true,
      "lang": "en",
      "date": "08 Jul",
      "datetime": "2026-07-08T12:31:20+00:00",
      "recent": true
    },
    {
      "id": "b77afc0c49b1",
      "cur": "NZD",
      "impact": "high",
      "title": "New Zealand Dollar: RBNZ hawkish path supports currency – BBH",
      "expand": "Brown Brothers Harriman’s (BBH) Elias Haddad reports that the Reserve Bank of New Zealand (RBNZ) delivered a 25 bps hike to 2.50%, largely priced in, triggering an New Zealand Dollar (NZD) rally before gains were trimmed by Middle East tensions.",
      "source": "FXStreet",
      "link": "https://www.fxstreet.com/news/new-zealand-dollar-rbnz-hawkish-path-supports-currency-bbh-202607081218",
      "time": "12:18",
      "ts": 1783513124000,
      "featured": true,
      "lang": "en",
      "date": "08 Jul",
      "datetime": "2026-07-08T12:18:44+00:00",
      "recent": true
    },
    {
      "id": "7e9550016ba3",
      "cur": "GBP",
      "impact": "med",
      "title": "Pound Sterling Price News and Forecast: GBP slumps against US Dollar as risky assets turn fragile",
      "expand": "The British Pound (GBP) is down 0.13% to near 1.3340 against the US Dollar (USD) during the European trading session on Wednesday. The GBP/USD pair faces selling pressure as renewed geopolitical risks have diminished the appeal of riskier assets.",
      "source": "FXStreet",
      "link": "https://www.fxstreet.com/news/pound-sterling-price-news-and-forecast-gbp-slumps-against-us-dollar-as-risky-assets-turn-fragile-202607081208",
      "time": "12:08",
      "ts": 1783512518000,
      "featured": false,
      "lang": "en",
      "date": "08 Jul",
      "datetime": "2026-07-08T12:08:38+00:00",
      "recent": true
    },
    {
      "id": "e4e06ccbd7f0",
      "cur": "USD",
      "impact": "high",
      "title": "US Dollar: Warsh risks skewed to cuts – Commerzbank",
      "expand": "Commerzbank’s Antje Praefcke argues that interest rate differentials are again driving the Dollar, with USD reacting strongly to weaker US data as markets reassess new Fed Chair Kevin Warsh.",
      "source": "FXStreet",
      "link": "https://www.fxstreet.com/news/us-dollar-warsh-risks-skewed-to-cuts-commerzbank-202607081207",
      "time": "12:07",
      "ts": 1783512466000,
      "featured": true,
      "lang": "en",
      "date": "08 Jul",
      "datetime": "2026-07-08T12:07:46+00:00",
      "recent": true
    },
    {
      "id": "d287b98c0cd2",
      "cur": "USD",
      "impact": "high",
      "title": "Oil: Conflict-driven volatility and positioning – BNY",
      "expand": "BNY’s Geoff Yu highlights growing fragility in global markets as President Trump declares the Iran ceasefire over and U.S. strikes in the Strait of Hormuz reignite Oil volatility.",
      "source": "FXStreet",
      "link": "https://www.fxstreet.com/news/oil-conflict-driven-volatility-and-positioning-bny-202607081157",
      "time": "11:57",
      "ts": 1783511826000,
      "featured": true,
      "lang": "en",
      "date": "08 Jul",
      "datetime": "2026-07-08T11:57:06+00:00",
      "recent": true
    },
    {
      "id": "300a32ec5c1b",
      "cur": "AUD",
      "impact": "low",
      "title": "Australian Dollar weakens on renewed Iran tensions ahead of Fed minutes",
      "expand": "AUD/USD falls to around 0.6920 on Wednesday at the time of writing, down 0.13% on the day after giving back its earlier gains.",
      "source": "FXStreet",
      "link": "https://www.fxstreet.com/news/australian-dollar-weakens-on-renewed-iran-tensions-ahead-of-fed-minutes-202607081135",
      "time": "11:35",
      "ts": 1783510510000,
      "featured": false,
      "lang": "en",
      "date": "08 Jul",
      "datetime": "2026-07-08T11:35:10+00:00",
      "recent": true
    },
    {
      "id": "7818c2afaf26",
      "cur": "SEK",
      "impact": "high",
      "title": "Swedish Krona: Growth strong, currency soft – Societe Generale",
      "expand": "Societe Generale’s Kit Juckes argues that Sweden’s strong growth and low inflation contrast with broader G10 dynamics, yet the Krona remains weak. He notes Sweden’s superior debt sustainability and recent data showing robust Gross Domestic Product (GDP) and minimal inflation.",
      "source": "FXStreet",
      "link": "https://www.fxstreet.com/news/swedish-krona-growth-strong-currency-soft-societe-generale-202607081132",
      "time": "11:32",
      "ts": 1783510345000,
      "featured": true,
      "lang": "en",
      "date": "08 Jul",
      "datetime": "2026-07-08T11:32:25+00:00",
      "recent": true
    },
    {
      "id": "194de3f89d6d",
      "cur": "CAD",
      "impact": "med",
      "title": "Canadian Dollar outperforms its peers amid rallying oil prices",
      "expand": "The Canadian Dollar (CAD) trades higher against its major currency peers, with USD/CAD sliding 0.26% to near 1.4160 during the European trading session on Wednesday.",
      "source": "FXStreet",
      "link": "https://www.fxstreet.com/news/canadian-dollar-outperforms-its-peers-amid-rallying-oil-prices-202607081118",
      "time": "11:18",
      "ts": 1783509513000,
      "featured": false,
      "lang": "en",
      "date": "08 Jul",
      "datetime": "2026-07-08T11:18:33+00:00",
      "recent": true
    },
    {
      "id": "cfd5551b5827",
      "cur": "EUR",
      "impact": "med",
      "title": "EUR/GBP Price Forecasts: Euro holds below 0.8450 with indicators showing some bullish divergence",
      "expand": "The Euro (EUR) is trading flat against the British Pound (GBP) on Wednesday, with bears contained above 0.8535 yet failing to find acceptance above 0.8650 so far.",
      "source": "FXStreet",
      "link": "https://www.fxstreet.com/news/eur-gbp-price-forecasts-euro-holds-below-08450-with-indicators-showing-some-bullish-divergence-202607081114",
      "time": "11:14",
      "ts": 1783509242000,
      "featured": false,
      "lang": "en",
      "date": "08 Jul",
      "datetime": "2026-07-08T11:14:02+00:00",
      "recent": true
    },
    {
      "id": "a4aa03570237",
      "cur": "GBP",
      "impact": "low",
      "title": "British Pound: Sterling supported as yields retrace – MUFG",
      "expand": "MUFG’s Derek Halpenny highlights that implied volatility in GBP/USD has barely moved after Nigel Farage’s decision to resign and recontest his Clacton seat, calling the by‑election a sham with potential further votes if he is sanctioned.",
      "source": "FXStreet",
      "link": "https://www.fxstreet.com/news/british-pound-sterling-supported-as-yields-retrace-mufg-202607081107",
      "time": "11:07",
      "ts": 1783508820000,
      "featured": false,
      "lang": "en",
      "date": "08 Jul",
      "datetime": "2026-07-08T11:07:00+00:00",
      "recent": true
    },
    {
      "id": "6aa9e7d175e4",
      "cur": "USD",
      "impact": "high",
      "title": "investingLive European morning session wrap: Oil prices surge as Trump calls off Iran deal",
      "expand": "Headlines: Trump says Memorandum of Understanding with Iran is over, don't want to engage with them US President Trump: Iran are dirty players, they are 'scum' Iran issues statement in condemning blatant violation to ceasefire deal by the US Oil prices jump as Trump says that Iran ceasefire deal is over Risk mood sours after Trump walks on Iran deal, threatens to cut trade ties with Spain Gold stays under pressure amid US-Iran escalation and increase in rate hike bets ECB's Escriva: Will keep all options on the table and decide on a meeting-by-meeting basis China reportedly decides to lift res...",
      "source": "Finnhub",
      "link": "https://investinglive.com/news/investinglive-european-morning-session-wrap-oil-prices-surge-as-trump-calls-off-iran-deal-20260708/",
      "time": "10:36",
      "ts": 1783507016000,
      "featured": true,
      "lang": "en",
      "date": "08 Jul",
      "datetime": "2026-07-08T10:36:56+00:00",
      "recent": true
    },
    {
      "id": "93c5e35f16dd",
      "cur": "NZD",
      "impact": "low",
      "title": "New Zealand Dollar gives away gains amid renewed tensions in the Middle East",
      "expand": "The New Zealand Dollar’s (NZD) rally against the US Dollar (USD) has been short-lived, as the pair returned to sub-0.5700 levels during the European session after being rejected at the 0.5725 area earlier in the day.",
      "source": "FXStreet",
      "link": "https://www.fxstreet.com/news/new-zealand-dollar-gives-away-gains-amid-renewed-tensions-in-the-middle-east-202607081027",
      "time": "10:27",
      "ts": 1783506420000,
      "featured": false,
      "lang": "en",
      "date": "08 Jul",
      "datetime": "2026-07-08T10:27:00+00:00",
      "recent": true
    },
    {
      "id": "66a3ae7da216",
      "cur": "USD",
      "impact": "high",
      "title": "US Dollar: FOMC minutes to highlight hawkish debate – TD Securities",
      "expand": "TD Securities strategists preview the June Federal Open Market Committee (FOMC) Minutes, expecting more insight into the policy debate than provided by Chair Warsh’s press conference.",
      "source": "FXStreet",
      "link": "https://www.fxstreet.com/news/us-dollar-fomc-minutes-to-highlight-hawkish-debate-td-securities-202607080957",
      "time": "09:57",
      "ts": 1783504655000,
      "featured": true,
      "lang": "en",
      "date": "08 Jul",
      "datetime": "2026-07-08T09:57:35+00:00",
      "recent": true
    },
    {
      "id": "e0d23e527771",
      "cur": "EUR",
      "impact": "med",
      "title": "EUR/USD Price Forecast: Euro hesitates above 1.1400 as geopolitical risks mount",
      "expand": "The Euro (EUR) shows marginal losses against the US Dollar (USD) on Wednesday and has returned to levels just above 1.1400 during the European trading session after rejection at 1.1430.",
      "source": "FXStreet",
      "link": "https://www.fxstreet.com/news/eur-usd-price-forecast-euro-hesitates-above-11400-as-geopolitical-risks-mount-202607080935",
      "time": "09:35",
      "ts": 1783503347000,
      "featured": false,
      "lang": "en",
      "date": "08 Jul",
      "datetime": "2026-07-08T09:35:47+00:00",
      "recent": true
    },
    {
      "id": "44e0eb6ab02f",
      "cur": "EUR",
      "impact": "high",
      "title": "ECB’s Escrivá: Central bank to keep all options on a meeting-by-meeting basis",
      "expand": "European Central Bank (ECB) policymaker and Governor of the Bank of Spain, José Luis Escrivá, said on Wednesday that the central bank “will keep all options on the table and decide on a meeting-by-meeting basis.”",
      "source": "FXStreet",
      "link": "https://www.fxstreet.com/news/ecbs-escriva-central-bank-to-keep-all-options-on-a-meeting-by-meeting-basis-202607080935",
      "time": "09:35",
      "ts": 1783503329000,
      "featured": true,
      "lang": "en",
      "date": "08 Jul",
      "datetime": "2026-07-08T09:35:29+00:00",
      "recent": true
    },
    {
      "id": "95ba5b20ef38",
      "cur": "USD",
      "impact": "high",
      "title": "Oil: Limited war risk keeps Brent capped – DBS",
      "expand": "DBS Group Research’s Philip Wee notes that recent Iranian strikes on shipping in the Strait of Hormuz pushed Brent crude from $72 to $76 per barrel and lifted US Treasury 2Y yields, but markets still see no return to full-scale war.",
      "source": "FXStreet",
      "link": "https://www.fxstreet.com/news/oil-limited-war-risk-keeps-brent-capped-dbs-202607080919",
      "time": "09:19",
      "ts": 1783502342000,
      "featured": true,
      "lang": "en",
      "date": "08 Jul",
      "datetime": "2026-07-08T09:19:02+00:00",
      "recent": true
    },
    {
      "id": "52892c979b53",
      "cur": "SEK",
      "impact": "low",
      "title": "Swedish Krona: Weakens against Euro – Societe Generale",
      "expand": "Societe Generale’s Kenneth Broux highlights EUR/SEK reclaiming its 200-day moving average and breaking above a base, signalling a short-term uptrend towards 11.11.",
      "source": "FXStreet",
      "link": "https://www.fxstreet.com/news/swedish-krona-weakens-against-euro-societe-generale-202607080908",
      "time": "09:08",
      "ts": 1783501725000,
      "featured": false,
      "lang": "en",
      "date": "08 Jul",
      "datetime": "2026-07-08T09:08:45+00:00",
      "recent": true
    },
    {
      "id": "0b26e2432508",
      "cur": "USD",
      "impact": "high",
      "title": "US Dollar: Fed pricing questioned as disinflation looms – MUFG",
      "expand": "MUFG’s Derek Halpenny argues that June FOMC minutes may already be stale as weaker labour data and lower energy prices challenge the Fed’s hawkish dot plot. He sees OIS pricing as too aggressive, with rate hikes over-priced and a rate cut by March 2027 more likely than another hike.",
      "source": "FXStreet",
      "link": "https://www.fxstreet.com/news/us-dollar-fed-pricing-questioned-as-disinflation-looms-mufg-202607080859",
      "time": "08:59",
      "ts": 1783501180000,
      "featured": true,
      "lang": "en",
      "date": "08 Jul",
      "datetime": "2026-07-08T08:59:40+00:00",
      "recent": true
    },
    {
      "id": "c4246f11f55d",
      "cur": "AUD",
      "impact": "low",
      "title": "Australian Dollar: Pullback within broader upside risk against US Dollar – UOB",
      "expand": "United Overseas Bank’s (UOB) Quek Ser Leang notes AUD/USD has retreated from recent highs after failing to clear resistance near 0.6980.",
      "source": "FXStreet",
      "link": "https://www.fxstreet.com/news/australian-dollar-pullback-within-broader-upside-risk-against-us-dollar-uob-202607080847",
      "time": "08:47",
      "ts": 1783500453000,
      "featured": false,
      "lang": "en",
      "date": "08 Jul",
      "datetime": "2026-07-08T08:47:33+00:00",
      "recent": true
    },
    {
      "id": "9e7110eb2e04",
      "cur": "USD",
      "impact": "high",
      "title": "Dow Jones futures fall on increasing risk aversion, FOMC Minutes awaited",
      "expand": "Dow Jones futures decline 0.40% to trade around 52,980 during European trading hours on Wednesday. Meanwhile, S P 500 futures and Nasdaq 100 futures fall 0.17% and 0.14%, trading near 7,540 and 29,350, respectively.",
      "source": "FXStreet",
      "link": "https://www.fxstreet.com/news/dow-jones-futures-fall-on-increasing-risk-aversion-fomc-minutes-awaited-202607080838",
      "time": "08:38",
      "ts": 1783499928000,
      "featured": true,
      "lang": "en",
      "date": "08 Jul",
      "datetime": "2026-07-08T08:38:48+00:00",
      "recent": true
    },
    {
      "id": "6a6e1ee1e6b6",
      "cur": "AUD",
      "impact": "high",
      "title": "Australian Dollar After RBA's Hunter Hawkish Remarks",
      "expand": "The Australian dollar strengthened against other major currencies in the Asian session on Wednesday, as the Reserve Bank of Australia (RBA) kept the door open for additional monetary policy tightening, if necessary, to bring inflation back to the central bank's target.",
      "source": "RTT News",
      "link": "https://www.rttnews.com/story.aspx?Id=3665356",
      "time": "07:16",
      "ts": 1783495000000,
      "featured": true,
      "lang": "en",
      "date": "08 Jul",
      "datetime": "2026-07-08T07:16:40+00:00",
      "recent": true
    },
    {
      "id": "7bf26cf17dcf",
      "cur": "AUD",
      "impact": "low",
      "title": "Australian Dollar Rises Against Majors",
      "expand": "The Australian dollar strengthened against other major currencies in the Asian session on Wednesday.",
      "source": "RTT News",
      "link": "https://www.rttnews.com/story.aspx?Id=3665342",
      "time": "06:49",
      "ts": 1783493362000,
      "featured": false,
      "lang": "en",
      "date": "08 Jul",
      "datetime": "2026-07-08T06:49:22+00:00",
      "recent": true
    },
    {
      "id": "53ac8035775c",
      "cur": "NZD",
      "impact": "high",
      "title": "New Zealand Central Bank Hikes Rate For First Time Since 2023",
      "expand": "The Reserve Bank of New Zealand raised its benchmark interest rate for the first time in more than three years to bring inflation to target and hinted at further tightening. The Monetary Policy Committee, governed by Anna Breman, decided to lift the Official Cash Rate by 25 basis points to 2.50 percent. This was the first hike since May 2023.",
      "source": "RTT News",
      "link": "https://www.rttnews.com/story.aspx?Id=3665300",
      "time": "05:42",
      "ts": 1783489379000,
      "featured": false,
      "lang": "en",
      "date": "08 Jul",
      "datetime": "2026-07-08T05:42:59+00:00",
      "recent": true
    },
    {
      "id": "bda12121141d",
      "cur": "NZD",
      "impact": "low",
      "title": "NZ Dollar Rises Against Majors",
      "expand": "The New Zealand dollar strengthened against other major currencies in the Asian session on Wednesday.",
      "source": "RTT News",
      "link": "https://www.rttnews.com/story.aspx?Id=3665288",
      "time": "05:17",
      "ts": 1783487864000,
      "featured": false,
      "lang": "en",
      "date": "08 Jul",
      "datetime": "2026-07-08T05:17:44+00:00",
      "recent": true
    },
    {
      "id": "0b903bcfb8ae",
      "cur": "NZD",
      "impact": "high",
      "title": "NZD/USD Recovers After RBNZ, but Higher Bar for Next Hike Caps Rally",
      "expand": "The New Zealand dollar received the boost that normally accompanies a rate hike, but the rally quickly lost momentum. The Reserve Bank of New Zealand delivered a widely anticipated 25 basis point increase in the Official Cash Rate to 2.50%, yet investors stopped short of pricing a more aggressive tightening cycle. Instead, the market came [&#8230;] The post NZD/USD Recovers After RBNZ, but Higher Bar for Next Hike Caps Rally appeared first on ActionForex .",
      "source": "ActionForex",
      "link": "https://www.actionforex.com/action-insight/market-overview/646506-nzd-usd-recovers-after-rbnz-but-higher-bar-for-next-hike-caps-rally/",
      "time": "03:00",
      "ts": 1783479637000,
      "featured": false,
      "lang": "en",
      "date": "08 Jul",
      "datetime": "2026-07-08T03:00:37+00:00",
      "recent": true
    },
    {
      "id": "beb26ac007be",
      "cur": "NZD",
      "impact": "high",
      "title": "RBNZ Raises OCR, Consensus Masks Diverging Inflation Views",
      "expand": "The Reserve Bank of New Zealand raised the Official Cash Rate by 25 basis points to 2.50%, with the Monetary Policy Committee reaching the decision by consensus despite differing assessments of the inflation outlook. Policymakers agreed that a further withdrawal of monetary stimulus was warranted to return inflation to the 2% midpoint, even though the [&#8230;] The post RBNZ Raises OCR, Consensus Masks Diverging Inflation Views appeared first on ActionForex .",
      "source": "ActionForex",
      "link": "https://www.actionforex.com/live-comments/646500-rbnz-raises-ocr-consensus-masks-diverging-inflation-views/",
      "time": "02:22",
      "ts": 1783477371000,
      "featured": false,
      "lang": "en",
      "date": "08 Jul",
      "datetime": "2026-07-08T02:22:51+00:00",
      "recent": true
    },
    {
      "id": "77e67c4ede94",
      "cur": "AUD",
      "impact": "high",
      "title": "RBA’s Hunter: Supply Shocks Don’t Mean Inflation Can Be Ignored",
      "expand": "Reserve Bank of Australia Assistant Governor Sarah Hunter said central banks cannot automatically dismiss inflation caused by supply shocks, arguing that persistent disruptions may still require a monetary policy response. &#8220;While supply shocks create difficult trade-offs, they do not lessen the importance of maintaining low and stable inflation,&#8221; she said, emphasizing that the RBA remains [&#8230;] The post RBA&#8217;s Hunter: Supply Shocks Don&#8217;t Mean Inflation Can Be Ignored appeared first on ActionForex .",
      "source": "ActionForex",
      "link": "https://www.actionforex.com/live-comments/646496-rbas-hunter-supply-shocks-dont-mean-inflation-can-be-ignored/",
      "time": "02:00",
      "ts": 1783476047000,
      "featured": false,
      "lang": "en",
      "date": "08 Jul",
      "datetime": "2026-07-08T02:00:47+00:00",
      "recent": true
    },
    {
      "id": "d71085bbe76d",
      "cur": "JPY",
      "impact": "high",
      "title": "BoJ’s Asada: Demand-Driven Inflation Needed Before Another Rate Hike",
      "expand": "Bank of Japan board member Toichiro Asada said he would only support another interest rate hike once inflation is clearly being driven by stronger domestic demand rather than temporary cost pressures. Speaking after dissenting against the BoJ&#8217;s June rate increase, Asada said, &#8220;I would support another rate hike only after confirming demand-driven inflation,&#8221; signaling that [&#8230;] The post BoJ&#8217;s Asada: Demand-Driven Inflation Needed Before Another Rate Hike appeared first on ActionForex .",
      "source": "ActionForex",
      "link": "https://www.actionforex.com/live-comments/646494-bojs-asada-demand-driven-inflation-needed-before-another-rate-hike/",
      "time": "01:57",
      "ts": 1783475834000,
      "featured": false,
      "lang": "en",
      "date": "08 Jul",
      "datetime": "2026-07-08T01:57:14+00:00",
      "recent": true
    },
    {
      "id": "44251d65e4a6",
      "cur": "AUD",
      "impact": "low",
      "title": "Chart Art: AUD/JPY Testing Support Turned Resistance Zone",
      "expand": "AUD/JPY recently fell through the floor around the 112.50 minor psychological mark and has since pulled up for a retest. Will the area of interest hold as a ceiling this time?",
      "source": "BabyPips",
      "link": "https://www.babypips.com/trading/chart-art-forex-audjpy-testing-support-resistance-zone-2026-07-08",
      "time": "01:37",
      "ts": 1783474620000,
      "featured": false,
      "lang": "en",
      "date": "08 Jul",
      "datetime": "2026-07-08T01:37:00+00:00",
      "recent": true
    },
    {
      "id": "056d052a23f7",
      "cur": "AUD",
      "impact": "high",
      "title": "Speech: Understanding Supply Shocks and Their Implications for Monetary Policy",
      "expand": "Speech by Sarah Hunter, Assistant Governor (Economic), to the Australian Conference of Economists 2026",
      "source": "RBA",
      "link": "https://www.rba.gov.au/speeches/2026/sp-ag-2026-07-08.html",
      "time": "01:00",
      "ts": 1783472400000,
      "featured": false,
      "lang": "en",
      "date": "08 Jul",
      "datetime": "2026-07-08T01:00:00+00:00",
      "recent": true
    },
    {
      "id": "f8fde867d53f",
      "cur": "JPY",
      "impact": "low",
      "title": "Yen Still Under Pressure: Markets Await Action from Authorities",
      "expand": "By Analytical Department RoboForex USD/JPY is holding near 161.84 on Tuesday, with the yen close to 40-year lows. Pressure on the Japanese currency remains as market participants continue to bet against it, with no visible currency interventions from Japanese authorities having materialised. At the same time, investors are closely monitoring potential action from Tokyo. Japanese [&#8230;]",
      "source": "InvestMacro",
      "link": "https://investmacro.com/2026/07/yen-still-under-pressure-markets-await-action-from-authorities/",
      "time": "13:41",
      "ts": 1783431697000,
      "featured": false,
      "lang": "en",
      "date": "07 Jul",
      "datetime": "2026-07-07T13:41:37+00:00",
      "recent": true
    },
    {
      "id": "24a6c7ee78fe",
      "cur": "NZD",
      "impact": "high",
      "title": "The Next Dollar Catalyst Is CPI. The Bigger Story Is Inside the Fed.",
      "expand": "Financial markets spent much of today&#8217;s session waiting rather than reacting. Most major currency pairs traded comfortably within yesterday&#8217;s ranges as investors resisted making large directional bets ahead of tomorrow&#8217;s RBNZ decision and next week&#8217;s US inflation report. Dollar and Yen were the day&#8217;s strongest performers, but neither attracted enough follow-through buying to establish fresh [&#8230;] The post The Next Dollar Catalyst Is CPI. The Bigger Story Is Inside the Fed. appeared first on ActionForex .",
      "source": "ActionForex",
      "link": "https://www.actionforex.com/action-insight/market-overview/646471-the-next-dollar-catalyst-is-cpi-the-bigger-story-is-inside-the-fed/",
      "time": "13:11",
      "ts": 1783429898000,
      "featured": false,
      "lang": "en",
      "date": "07 Jul",
      "datetime": "2026-07-07T13:11:38+00:00",
      "recent": true
    },
    {
      "id": "40f7adf6de05",
      "cur": "SEK",
      "impact": "low",
      "title": "ESRB warns of vulnerabilities in the financial system linked to frontier AI models",
      "expand": "The European Systemic Risk Board (ESRB), the EU’s macroprudential oversight authority, is issuing a formal warning regarding vulnerabilities in the financial system linked to frontier AI models. The ESRB's warning calls for relevant authorities to reflect these risks in supervisory and oversight work.",
      "source": "Riksbank",
      "link": "https://www.riksbank.se/en-gb/press-and-published/notices-and-press-releases/press-releases/2026/esrb-warns-of-vulnerabilities-in-the-financial-system-linked-to-frontier-ai-models/",
      "time": "09:30",
      "ts": 1783416611000,
      "featured": false,
      "lang": "en",
      "date": "07 Jul",
      "datetime": "2026-07-07T09:30:11+00:00",
      "recent": false
    },
    {
      "id": "334826c8e6eb",
      "cur": "EUR",
      "impact": "high",
      "title": "ECB’s Panetta: Fragile Outlook Means No Predetermined Path for Rates",
      "expand": "European Central Bank Governing Council member Fabio Panetta said the Eurozone economy continues to face a delicate balance between persistent inflation risks and weakening growth, arguing that policymakers should avoid committing to any predetermined path for interest rates. &#8220;The outlook remains fragile. Upside risks to inflation continue to coexist with downside risks to growth,&#8221; he [&#8230;] The post ECB&#8217;s Panetta: Fragile Outlook Means No Predetermined Path for Rates appeared first on ActionForex .",
      "source": "ActionForex",
      "link": "https://www.actionforex.com/live-comments/646415-ecbs-panetta-fragile-outlook-means-no-predetermined-path-for-rates/",
      "time": "09:06",
      "ts": 1783415196000,
      "featured": false,
      "lang": "en",
      "date": "07 Jul",
      "datetime": "2026-07-07T09:06:36+00:00",
      "recent": false
    },
    {
      "id": "cf184e0b4419",
      "cur": "GBP",
      "impact": "low",
      "title": "GBP/CHF Nears Trend-Reversal Zone as Political Risk Fades and Sterling Shorts Unwind",
      "expand": "Sterling&#8217;s rally has been about more than better sentiment toward the UK. It has been driven by the disappearance of one of the market&#8217;s biggest bearish trades. As political uncertainty faded following the resolution of Labour&#8217;s leadership transition, investors who had built sizeable short Sterling positions found themselves on the wrong side of the market. [&#8230;] The post GBP/CHF Nears Trend-Reversal Zone as Political Risk Fades and Sterling Shorts Unwind appeared first on ActionForex .",
      "source": "ActionForex",
      "link": "https://www.actionforex.com/action-insight/market-overview/646391-gbp-chf-nears-trend-reversal-zone-as-political-risk-fades-and-sterling-shorts-unwind/",
      "time": "04:05",
      "ts": 1783397140000,
      "featured": false,
      "lang": "en",
      "date": "07 Jul",
      "datetime": "2026-07-07T04:05:40+00:00",
      "recent": false
    },
    {
      "id": "23819b5724f2",
      "cur": "NZD",
      "impact": "low",
      "title": "FX Watch: NZD/USD and GBP/NZD Setups if RBNZ Weighs on the Kiwi",
      "expand": "If the RBNZ sounds less upbeat on the Kiwi, then GBP/NZD and NZD/USD could offer interesting setups for NZD traders.",
      "source": "BabyPips",
      "link": "https://www.babypips.com/analysis/fx-watch-gbpnzd-nzdusd-setups-if-rbnz-weighs-on-kiwi-2026-07-07",
      "time": "03:16",
      "ts": 1783394160000,
      "featured": false,
      "lang": "en",
      "date": "07 Jul",
      "datetime": "2026-07-07T03:16:00+00:00",
      "recent": false
    },
    {
      "id": "cee79ca4a22e",
      "cur": "EUR",
      "impact": "high",
      "title": "ECB’s Schnabel: Falling Oil Prices Don’t Mean Inflation Battle Is Over",
      "expand": "European Central Bank Executive Board member Isabel Schnabel cautioned that the recent decline in oil prices should not be interpreted as a return to pre-war inflation conditions, arguing that underlying price pressures remain elevated. &#8220;Does the decline in oil prices mean that we are back to the pre-war situation? I don&#8217;t think so,&#8221; she said [&#8230;] The post ECB&#8217;s Schnabel: Falling Oil Prices Don&#8217;t Mean Inflation Battle Is Over appeared first on ActionForex .",
      "source": "ActionForex",
      "link": "https://www.actionforex.com/live-comments/646382-ecbs-schnabel-falling-oil-prices-dont-mean-inflation-battle-is-over/",
      "time": "02:40",
      "ts": 1783392021000,
      "featured": false,
      "lang": "en",
      "date": "07 Jul",
      "datetime": "2026-07-07T02:40:21+00:00",
      "recent": false
    },
    {
      "id": "25ea46e99703",
      "cur": "AUD",
      "impact": "low",
      "title": "Chart Art: AUD/CAD Gearing Up for Another Test of Range Resistance",
      "expand": "AUD/CAD continues to pace back and forth between support and resistance on its 4-hour time frame. Will it bounce off the top again soon?",
      "source": "BabyPips",
      "link": "https://www.babypips.com/trading/chart-art-forex-audcad-gearing-up-another-test-range-resistance-2026-07-07",
      "time": "02:17",
      "ts": 1783390620000,
      "featured": false,
      "lang": "en",
      "date": "07 Jul",
      "datetime": "2026-07-07T02:17:00+00:00",
      "recent": false
    },
    {
      "id": "20151e8f6883",
      "cur": "AUD",
      "impact": "high",
      "title": "FX Watch: NZD/CHF and AUD/NZD Trend Lines for a Hawkish RBNZ Decision",
      "expand": "Will the RBNZ hike interest rates and signal scope for further tightening? Here’s what I’m watching on NZD/CHF and AUD/NZD if this happens.",
      "source": "BabyPips",
      "link": "https://www.babypips.com/analysis/watchlist-forex-nzdchf-aunzd-trend-lines-hawkish-rbnz-2026-07-07",
      "time": "02:05",
      "ts": 1783389900000,
      "featured": false,
      "lang": "en",
      "date": "07 Jul",
      "datetime": "2026-07-07T02:05:00+00:00",
      "recent": false
    },
    {
      "id": "b79aea1b7611",
      "cur": "NZD",
      "impact": "high",
      "title": "Event Guide: RBNZ Monetary Policy Statement (July 2026)",
      "expand": "With a July rate hike back in play, the RBNZ’s next decision could give Kiwi increased volatilty in the next trading sessions.",
      "source": "BabyPips",
      "link": "https://www.babypips.com/analysis/event-guide-forex-new-zealand-rbnz-monetary-policy-decision-july-2026-07-07",
      "time": "01:33",
      "ts": 1783387980000,
      "featured": false,
      "lang": "en",
      "date": "07 Jul",
      "datetime": "2026-07-07T01:33:00+00:00",
      "recent": false
    },
    {
      "id": "4795b65eaed3",
      "cur": "AUD",
      "impact": "med",
      "title": "Australian Dollar Price Forecast: Has the recovery kicked in?",
      "expand": "The Aussie Dollar remains in a consolidative phase below the key 0.7000 threshold for now, while the constructive tone remains unchanged above the critical 200-day SMA.",
      "source": "FXStreet",
      "link": "https://www.fxstreet.com/analysis/australian-dollar-price-forecast-has-the-recovery-kicked-in-202607061723",
      "time": "17:23",
      "ts": 1783358624000,
      "featured": false,
      "lang": "en",
      "date": "06 Jul",
      "datetime": "2026-07-06T17:23:44+00:00",
      "recent": false
    },
    {
      "id": "5ee9e3110aee",
      "cur": "CAD",
      "impact": "med",
      "title": "Oil prices have stabilized. The Canadian dollar continues to trade near yearly lows.",
      "expand": "By JustMarkets On Friday, US indices were not traded due to a public holiday in the United States. By the end of the week, the Dow Jones Index (US30) rose by 2.12%. The S&#38;P 500 Index (US500) gained 2.33%. The Technology‑heavy NASDAQ Index (US100) closed higher by 1.00% over five trading days. This week, market [&#8230;]",
      "source": "InvestMacro",
      "link": "https://investmacro.com/2026/07/oil-prices-have-stabilized-the-canadian-dollar-continues-to-trade-near-yearly-lows/",
      "time": "13:41",
      "ts": 1783345260000,
      "featured": false,
      "lang": "en",
      "date": "06 Jul",
      "datetime": "2026-07-06T13:41:00+00:00",
      "recent": false
    },
    {
      "id": "559dbe684d61",
      "cur": "EUR",
      "impact": "high",
      "title": "EUR/USD in a Narrow Range: Focus on Fed Minutes",
      "expand": "By Analytical Department RoboForex EUR/USD is trading around 1.1432 on Monday. At the end of last week, the main currency pair posted modest gains. Weaker-than-expected US labour market data and lower oil prices have weighed on the US dollar, prompting investors to reconsider expectations for further Federal Reserve policy tightening. The Non-Farm Payrolls report released [&#8230;]",
      "source": "InvestMacro",
      "link": "https://investmacro.com/2026/07/eur-usd-in-a-narrow-range-focus-on-fed-minutes/",
      "time": "13:39",
      "ts": 1783345147000,
      "featured": false,
      "lang": "en",
      "date": "06 Jul",
      "datetime": "2026-07-06T13:39:07+00:00",
      "recent": false
    },
    {
      "id": "7b2e30ccb6fc",
      "cur": "JPY",
      "impact": "high",
      "title": "USD/JPY Bulls Return as Japan’s Intervention Window Closes",
      "expand": "USD/JPY bulls are back. After last week&#8217;s intervention scare briefly knocked the pair lower, Yen selling returned today as the most obvious window for Japanese action passed without official intervention. Dollar&#8217;s rebound also helped, with markets now appearing to have fully absorbed the dovish surprise from June non-farm payrolls. But the sharper story is in [&#8230;] The post USD/JPY Bulls Return as Japan&#8217;s Intervention Window Closes appeared first on ActionForex .",
      "source": "ActionForex",
      "link": "https://www.actionforex.com/action-insight/market-overview/646339-usd-jpy-bulls-return-as-japans-intervention-window-closes/",
      "time": "12:53",
      "ts": 1783342405000,
      "featured": false,
      "lang": "en",
      "date": "06 Jul",
      "datetime": "2026-07-06T12:53:25+00:00",
      "recent": false
    },
    {
      "id": "1176e669885f",
      "cur": "EUR",
      "impact": "low",
      "title": "Eurozone Producer Inflation Holds Firm as Core Factory Prices Continue to Rise",
      "expand": "Eurozone PPI rose 0.2% mom in May, matching market expectations, while annual producer inflation accelerated from 5.0% yoy to 5.9% yoy, slightly above the 5.7% yoy consensus. The data suggest producer price pressures remained elevated even as monthly price growth moderated from April&#8217;s 0.7% increase. The monthly increase reflected diverging trends across sectors. Prices for [&#8230;] The post Eurozone Producer Inflation Holds Firm as Core Factory Prices Continue to Rise appeared first on ActionForex .",
      "source": "ActionForex",
      "link": "https://www.actionforex.com/live-comments/646273-eurozone-producer-inflation-holds-firm-as-core-factory-prices-continue-to-rise/",
      "time": "09:19",
      "ts": 1783329573000,
      "featured": false,
      "lang": "en",
      "date": "06 Jul",
      "datetime": "2026-07-06T09:19:33+00:00",
      "recent": false
    },
    {
      "id": "d20631ba8306",
      "cur": "EUR",
      "impact": "med",
      "title": "Eurozone Retail Sales Rise 0.2% mom in May as Food Spending Leads Growth",
      "expand": "Eurozone retail sales rose 0.2% mom in May, matching market expectations and pointing to continued resilience in consumer spending despite a mixed performance across retail categories. Across the broader EU, retail sales increased a stronger 0.5% mom, suggesting consumer demand remained relatively firm in several member states. The monthly increase in the Eurozone was driven [&#8230;] The post Eurozone Retail Sales Rise 0.2% mom in May as Food Spending Leads Growth appeared first on ActionForex .",
      "source": "ActionForex",
      "link": "https://www.actionforex.com/live-comments/646268-eurozone-retail-sales-rise-0-2-mom-in-may-as-food-spending-leads-growth/",
      "time": "09:11",
      "ts": 1783329109000,
      "featured": false,
      "lang": "en",
      "date": "06 Jul",
      "datetime": "2026-07-06T09:11:49+00:00",
      "recent": false
    },
    {
      "id": "bb9cfefbea65",
      "cur": "EUR",
      "impact": "low",
      "title": "Eurozone Sentix Investor Confidence Surges to -3.1 as Germany’s Recovery Gains Traction",
      "expand": "Eurozone investor confidence improved sharply in July, with the Sentix Investor Confidence Index rising from -13.4 to -3.1, marking a third consecutive monthly gain. The improvement was broad-based, with the Current Situation Index climbing from -20.0 to -14.8, while the Expectations Index jumped from -6.5 to 9.3, returning to positive territory as optimism over the [&#8230;] The post Eurozone Sentix Investor Confidence Surges to -3.1 as Germany&#8217;s Recovery Gains Traction appeared first on ActionForex .",
      "source": "ActionForex",
      "link": "https://www.actionforex.com/live-comments/646264-eurozone-sentix-investor-confidence-surges-to-3-1-as-germanys-recovery-gains-traction/",
      "time": "08:40",
      "ts": 1783327255000,
      "featured": false,
      "lang": "en",
      "date": "06 Jul",
      "datetime": "2026-07-06T08:40:55+00:00",
      "recent": false
    },
    {
      "id": "46fbfe65b996",
      "cur": "CHF",
      "impact": "high",
      "title": "The US Dollar just beat the Swiss Franc at its own safe-haven game",
      "expand": "As the king among safe havens, the Swiss Franc (CHF) is supposed to benefit from geopolitical shocks such as the Iran war. This time, it didn’t.",
      "source": "FXStreet",
      "link": "https://www.fxstreet.com/analysis/the-us-dollar-just-beat-the-swiss-franc-at-its-own-safe-haven-game-202607060655",
      "time": "06:55",
      "ts": 1783320911000,
      "featured": false,
      "lang": "en",
      "date": "06 Jul",
      "datetime": "2026-07-06T06:55:11+00:00",
      "recent": false
    },
    {
      "id": "92d6bb1e19d3",
      "cur": "EUR",
      "impact": "low",
      "title": "CEE: Saving rate in the EU",
      "expand": "The EU27 and Eurozone series followed a very similar trajectory since 2015, with the Eurozone consistently recording slightly higher values than the EU average.",
      "source": "FXStreet",
      "link": "https://www.fxstreet.com/analysis/cee-saving-rate-in-the-eu-202607060643",
      "time": "06:43",
      "ts": 1783320199000,
      "featured": false,
      "lang": "en",
      "date": "06 Jul",
      "datetime": "2026-07-06T06:43:19+00:00",
      "recent": false
    },
    {
      "id": "1da163b43b64",
      "cur": "NZD",
      "impact": "low",
      "title": "NZD/USD Bears Await RBNZ Verdict After Relief Rally",
      "expand": "Last week&#8217;s post-US NFP rebound has given NZD/USD some breathing room, but it has done little to convince traders that the recent downtrend has run its course. With the Reserve Bank of New Zealand set to announce its policy decision this week, the Kiwi now faces a catalyst that could determine whether the recovery develops [&#8230;] The post NZD/USD Bears Await RBNZ Verdict After Relief Rally appeared first on ActionForex .",
      "source": "ActionForex",
      "link": "https://www.actionforex.com/action-insight/market-overview/646249-nzd-usd-bears-await-rbnz-verdict-after-relief-rally/",
      "time": "02:33",
      "ts": 1783305234000,
      "featured": false,
      "lang": "en",
      "date": "06 Jul",
      "datetime": "2026-07-06T02:33:54+00:00",
      "recent": false
    }
  ]
}